gspread_rpa/__init__.py
gspread_rpa/format_cell.py
gspread_rpa/gspreadsheet_retry.py
gspread_rpa/retry.py
gspread_rpa/demo/00-demo-index-00.py
gspread_rpa/demo/01-demo-create-00.py
gspread_rpa/demo/01-demo-create-01.py
gspread_rpa/demo/02-demo-data-00.py
gspread_rpa/demo/02-demo-data-01.py
gspread_rpa/demo/02-demo-data-02.py
gspread_rpa/demo/02-demo-data-03.py
gspread_rpa/demo/03-demo-revision-00.py
gspread_rpa/demo/03-demo-revision-01.py
gspread_rpa/demo/03-demo-revision-02.py
gspread_rpa/demo/04-demo-formatting-00.py
gspread_rpa/demo/04-demo-formatting-01.py
gspread_rpa/demo/04-demo-formatting-02.py
gspread_rpa/demo/05-demo-lookup-00.py
gspread_rpa/demo/05-demo-lookup-01.py
gspread_rpa/demo/Makefile
gspread_rpa/demo/make.bat
gspread_rpa-1.0.2.dist-info/LICENSE
gspread_rpa-1.0.2.dist-info/METADATA
gspread_rpa-1.0.2.dist-info/WHEEL
gspread_rpa-1.0.2.dist-info/top_level.txt
gspread_rpa-1.0.2.dist-info/RECORD
